botrun_keys_mgr/__init__.py
botrun_keys_mgr/__main__.py
botrun_keys_mgr/key_data.py
botrun_keys_mgr/key_manager.py
botrun_keys_mgr-0.1.0.dist-info/METADATA
botrun_keys_mgr-0.1.0.dist-info/WHEEL
botrun_keys_mgr-0.1.0.dist-info/RECORD
