Metadata-Version: 2.3
Name: botrun-keys-mgr
Version: 0.1.0
Summary: 波特人 API 金鑰管理套件
Author: sebastian-hsu
Author-email: sebastian.hsu@gmail.com
Requires-Python: >=3.11,<4.0
Classifier: Programming Language :: Python :: 3
Classifier: Programming Language :: Python :: 3.11
Classifier: Programming Language :: Python :: 3.12
Classifier: Programming Language :: Python :: 3.13
Requires-Dist: google-api-python-client (>=2.159.0,<3.0.0)
Requires-Dist: google-auth (>=2.37.0,<3.0.0)
Requires-Dist: pandas (>=2.2.3,<3.0.0)
